{
"companyName": "GloverCorp",
"productName": "Pong",
"productVersion": "0.1",
"dataUrl": "Pong.v1.2.GL.data.unityweb",
"wasmCodeUrl": "Pong.v1.2.GL.wasm.code.unityweb",
"wasmFrameworkUrl": "Pong.v1.2.GL.wasm.framework.unityweb",
"graphicsAPI": ["WebGL 2.0","WebGL 1.0"],
"webglContextAttributes": {"preserveDrawingBuffer": false},
"splashScreenStyle": "Dark",
"backgroundColor": "#231F20",
"cacheControl": {"default": "must-revalidate"},
"developmentBuild": false,
"multithreading": false,
"unityVersion": "2019.2.3f1"
}